simple_pub_sub/__init__.py
simple_pub_sub/backends.py
simple_pub_sub/message.py
simple_pub_sub/publisher.py
simple_pub_sub/subscriber.py
SimplePubSub-0.1.0.dist-info/METADATA
SimplePubSub-0.1.0.dist-info/WHEEL
SimplePubSub-0.1.0.dist-info/top_level.txt
SimplePubSub-0.1.0.dist-info/RECORD
