Metadata-Version: 2.1
Name: SimplePubSub
Version: 0.1.0
Summary: UNKNOWN
Home-page: UNKNOWN
Author: UNKNOWN
Author-email: jack@mizar.ai, cuici@mizar.ai, alex@mizar.ai, cino@mizar.ai
License: UNKNOWN
Platform: UNKNOWN
Requires-Dist: redis
Requires-Dist: pytest
